gtirb_functions/__init__.py
gtirb_functions/__main__.py
gtirb_functions/function.py
gtirb_functions/py.typed
gtirb_functions/version.py
gtirb_functions-1.0.9.dist-info/DESCRIPTION.rst
gtirb_functions-1.0.9.dist-info/METADATA
gtirb_functions-1.0.9.dist-info/RECORD
gtirb_functions-1.0.9.dist-info/WHEEL
gtirb_functions-1.0.9.dist-info/entry_points.txt
gtirb_functions-1.0.9.dist-info/metadata.json
gtirb_functions-1.0.9.dist-info/top_level.txt
