Metadata-Version: 2.0
Name: gtirb-functions
Version: 1.0.9
Summary: Utilities for dealing with functions in GTIRB
Home-page: https://github.com/grammatech/gtirb-functions
Author: Grammatech
Author-email: gtirb@grammatech.com
License: MIT
Platform: UNKNOWN
Classifier: Programming Language :: Python :: 3
Requires-Dist: gtirb
